universal_mcp_serpapi/README.md
universal_mcp_serpapi/__init__.py
universal_mcp_serpapi/app.py
universal_mcp_serpapi/server.py
universal_mcp_serpapi-0.1.10.dist-info/METADATA
universal_mcp_serpapi-0.1.10.dist-info/WHEEL
universal_mcp_serpapi-0.1.10.dist-info/entry_points.txt
universal_mcp_serpapi-0.1.10.dist-info/licenses/LICENSE
universal_mcp_serpapi-0.1.10.dist-info/RECORD
